depythel/__init__.py
depythel/_utility_imports.py
depythel/main.py
depythel/py.typed
depythel/repository/.DS_Store
depythel/repository/__init__.py
depythel/repository/aur.py
depythel/repository/homebrew.py
depythel/repository/macports.py
depythel_api-0.1.0.dist-info/WHEEL
depythel_api-0.1.0.dist-info/METADATA
depythel_api-0.1.0.dist-info/RECORD
