Metadata-Version: 2.1
Name: depythel-api
Version: 0.1.0
Summary: Library for Interdependency Visualiser and Dependency Hell scrutiniser
License: GPL-3.0-or-later
Author: harens
Author-email: harensdeveloper@gmail.com
Requires-Python: >=3.7,<4.0
Classifier: License :: OSI Approved :: GNU General Public License v3 or later (GPLv3+)
Classifier: Programming Language :: Python :: 3
Classifier: Programming Language :: Python :: 3.7
Classifier: Programming Language :: Python :: 3.8
Classifier: Programming Language :: Python :: 3.9
Classifier: Programming Language :: Python :: 3.10
